<annotation>
	<folder>motorbike</folder>
	<filename>2H8RPE7ACI1P.jpg</filename>
	<path>C:\Users\roel2\PycharmProjects\ObjectDetection\models\research\object_detection\images\train\motorbike\2H8RPE7ACI1P.jpg</path>
	<source>
		<database>Unknown</database>
	</source>
	<size>
		<width>183</width>
		<height>123</height>
		<depth>3</depth>
	</size>
	<segmented>0</segmented>
	<object>
		<name>motorcycle</name>
		<pose>Unspecified</pose>
		<truncated>0</truncated>
		<difficult>0</difficult>
		<bndbox>
			<xmin>3</xmin>
			<ymin>26</ymin>
			<xmax>182</xmax>
			<ymax>115</ymax>
		</bndbox>
	</object>
</annotation>
